sharesight/__init__.py
sharesight/auth.py
sharesight/base.py
sharesight/client.py
sharesight/exceptions.py
sharesight/holdings.py
sharesight/investments.py
sharesight/market.py
sharesight/portfolios.py
sharesight/reports.py
sharesight/trades.py
sharesight_python-0.1.2.dist-info/METADATA
sharesight_python-0.1.2.dist-info/WHEEL
sharesight_python-0.1.2.dist-info/licenses/LICENSE
sharesight_python-0.1.2.dist-info/RECORD
