Metadata-Version: 2.4
Name: sharesight-python
Version: 0.1.2
Summary: An unofficial Python SDK for the Sharesight API (v2 and v3)
Project-URL: Homepage, https://github.com/dejersey/sharesight-python
Project-URL: Documentation, https://github.com/dejersey/sharesight-python#readme
Project-URL: Repository, https://github.com/dejersey/sharesight-python.git
Project-URL: Issues, https://github.com/dejersey/sharesight-python/issues
Author-email: Peter de Jersey <peter.dejersey@me.com>
License-Expression: MIT
License-File: LICENSE
Keywords: api,investing,portfolio,sdk,sharesight,stocks
Classifier: Development Status :: 4 - Beta
Classifier: Intended Audience :: Developers
Classifier: License :: OSI Approved :: MIT License
Classifier: Operating System :: OS Independent
Classifier: Programming Language :: Python :: 3
Classifier: Programming Language :: Python :: 3.8
Classifier: Programming Language :: Python :: 3.9
Classifier: Programming Language :: Python :: 3.10
Classifier: Programming Language :: Python :: 3.11
Classifier: Programming Language :: Python :: 3.12
Classifier: Topic :: Office/Business :: Financial :: Investment
Requires-Python: >=3.8
Requires-Dist: httpx>=0.24.0
